vc2_quantisation_matrices/__init__.py
vc2_quantisation_matrices/cli_tool.py
vc2_quantisation_matrices/version.py
vc2_quantisation_matrices-1.0.0.dist-info/LICENSE.txt
vc2_quantisation_matrices-1.0.0.dist-info/METADATA
vc2_quantisation_matrices-1.0.0.dist-info/WHEEL
vc2_quantisation_matrices-1.0.0.dist-info/entry_points.txt
vc2_quantisation_matrices-1.0.0.dist-info/top_level.txt
vc2_quantisation_matrices-1.0.0.dist-info/RECORD
