Metadata-Version: 2.1
Name: vc2-quantisation-matrices
Version: 1.0.0
Summary: Routines for computing quantisation matrices for the SMPTE ST 2042-2 VC-2 professional video codec.
Home-page: https://github.com/bbc/vc2_quantisation_matrices
Author: BBC R&D
License: GPL-3.0-only
Keywords: smpte-RP-2042-3 vc2 dirac dirac-pro quantisation-matrix bit-width
Platform: UNKNOWN
Classifier: Development Status :: 5 - Production/Stable
Classifier: Intended Audience :: Developers
Classifier: Intended Audience :: Manufacturing
Classifier: Intended Audience :: Information Technology
Classifier: Intended Audience :: Telecommunications Industry
Classifier: License :: OSI Approved :: GNU General Public License v3 (GPLv3)
Classifier: Operating System :: POSIX :: Linux
Classifier: Operating System :: Microsoft :: Windows
Classifier: Operating System :: MacOS
Classifier: Programming Language :: Python :: 3
Classifier: Programming Language :: Python :: 3 :: Only
Classifier: Programming Language :: Python :: 3.6
Classifier: Programming Language :: Python :: 3.7
Classifier: Programming Language :: Python :: 3.8
Classifier: Programming Language :: Python :: 3.9
Requires-Dist: vc2-data-tables (<2.0,>=0.1)
Requires-Dist: sympy
